TableQAKit/__init__.py
TableQAKit/app.py
TableQAKit/cli.py
TableQAKit/gunicorn_config.py
TableQAKit/icl/__init__.py
TableQAKit/icl/dataset.py
TableQAKit/icl/infer.py
TableQAKit/icl/model.py
TableQAKit/icl/utils.py
TableQAKit/llama/Trainer.py
TableQAKit/llama/__init__.py
TableQAKit/llama/data_collator.py
TableQAKit/llama/dataset.py
TableQAKit/llama/model.py
TableQAKit/llama/peft_trainer.py
TableQAKit/llama/seq2seq.py
TableQAKit/llama/template.py
TableQAKit/llama/utils.py
TableQAKit/loaders/FinQA.py
TableQAKit/loaders/HiTab.py
TableQAKit/loaders/HybridQA.py
TableQAKit/loaders/MultiHiertt.py
TableQAKit/loaders/MultimodalQA.py
TableQAKit/loaders/SpreadSheetQA.py
TableQAKit/loaders/TATQA.py
TableQAKit/loaders/WikiSQL.py
TableQAKit/loaders/WikiTableQuestions.py
TableQAKit/loaders/__init__.py
TableQAKit/mmqa_utils/__init__.py
TableQAKit/mmqa_utils/test_classifier.py
TableQAKit/mmqa_utils/test_mmhqa_icl.py
TableQAKit/mmqa_utils/test_retriever.py
TableQAKit/mmqa_utils/classifier_module/__init__.py
TableQAKit/mmqa_utils/classifier_module/dataset.py
TableQAKit/mmqa_utils/classifier_module/model.py
TableQAKit/mmqa_utils/classifier_module/trainer.py
TableQAKit/mmqa_utils/classifier_module/utils.py
TableQAKit/mmqa_utils/mmhqa_icl/__init__.py
TableQAKit/mmqa_utils/mmhqa_icl/args.py
TableQAKit/mmqa_utils/mmhqa_icl/main.py
TableQAKit/mmqa_utils/mmhqa_icl/mmqa.py
TableQAKit/mmqa_utils/mmhqa_icl/utils.py
TableQAKit/mmqa_utils/mmhqa_icl/qa/__init__.py
TableQAKit/mmqa_utils/mmhqa_icl/qa/openai_qa.py
TableQAKit/mmqa_utils/mmhqa_icl/qa/prompt.py
TableQAKit/mmqa_utils/retriever_module/__init__.py
TableQAKit/mmqa_utils/retriever_module/dataset.py
TableQAKit/mmqa_utils/retriever_module/model.py
TableQAKit/mmqa_utils/retriever_module/trainer.py
TableQAKit/mmqa_utils/retriever_module/utils.py
TableQAKit/mmqa_utils/utils/__init__.py
TableQAKit/mmqa_utils/utils/eval_retriever.py
TableQAKit/mmqa_utils/utils/image_stuff.py
TableQAKit/mmqa_utils/utils/retriever.py
TableQAKit/multihop/__init__.py
ttqakit-1.0.0.dist-info/LICENSE
ttqakit-1.0.0.dist-info/METADATA
ttqakit-1.0.0.dist-info/WHEEL
ttqakit-1.0.0.dist-info/entry_points.txt
ttqakit-1.0.0.dist-info/top_level.txt
ttqakit-1.0.0.dist-info/RECORD
