Metadata-Version: 2.1
Name: ttqakit
Version: 1.0.0
Summary: TTQAKit: A toolkit for Text-Table Hybrid Question Answering.
Home-page: https://github.com/lfy79001/TextTableQAKit
Author: Fangyu Lei
Author-email: leifangyu@qq.com
License: Apache-2.0 License
Classifier: Development Status :: 3 - Alpha
Classifier: Programming Language :: Python :: 3.7
Classifier: Programming Language :: Python :: 3.8
Classifier: Programming Language :: Python :: 3.9
Classifier: Programming Language :: Python :: 3.10
Classifier: Intended Audience :: Science/Research
Classifier: Operating System :: POSIX :: Linux
Classifier: License :: OSI Approved :: Apache Software License
Classifier: Topic :: Scientific/Engineering :: Artificial Intelligence
Classifier: Topic :: Software Development :: Libraries :: Python Modules
Classifier: Typing :: Typed
Requires-Python: >=3.7
License-File: LICENSE
Requires-Dist: Flask (>=2.2.2)
Requires-Dist: datasets (>=2.9.0)
Requires-Dist: requests
Requires-Dist: lxml
Requires-Dist: tinyhtml
Requires-Dist: xlsxwriter
Requires-Dist: coloredlogs
Provides-Extra: deploy
Requires-Dist: gunicorn ; extra == 'deploy'
Provides-Extra: dev
Requires-Dist: wheel ; extra == 'dev'
Requires-Dist: black ; extra == 'dev'
